pypostegres/__init__.py
pypostegres/cli.py
pypostegres/colors.py
pypostegres/config.py
pypostegres/connection.py
pypostegres/data_manager.py
pypostegres/main.py
pypostegres/pretty_printer.py
pypostegres/query_builder.py
pypostegres/schema.py
my_py_postgres-0.1.0.dist-info/METADATA
my_py_postgres-0.1.0.dist-info/WHEEL
my_py_postgres-0.1.0.dist-info/entry_points.txt
my_py_postgres-0.1.0.dist-info/top_level.txt
my_py_postgres-0.1.0.dist-info/RECORD
