Metadata-Version: 2.2
Name: my-py-postgres
Version: 0.1.0
Summary: PostgreSQL database management system with a user-friendly interface
Home-page: https://github.com/Ayman-aa/pypostgres
Author: Ayman Aamam
Author-email: aymaneaamam@gmail.com
Classifier: Programming Language :: Python :: 3
Classifier: License :: OSI Approved :: MIT License
Classifier: Operating System :: OS Independent
Requires-Python: >=3.6
Requires-Dist: psycopg2-binary>=2.9.0
Requires-Dist: click>=8.1.6
Requires-Dist: rich>=13.7.1
Dynamic: author
Dynamic: author-email
Dynamic: classifier
Dynamic: description
Dynamic: description-content-type
Dynamic: home-page
Dynamic: requires-dist
Dynamic: requires-python
Dynamic: summary
